[
  {
    "path": "articles/",
    "title": "About Me",
    "description": {},
    "author": [
      {
        "name": "Taylor",
        "url": {}
      }
    ],
    "date": "2021-03-15",
    "categories": [],
    "contents": "\r\nInterests\r\nI love baking (anything sourdough!), crafts like macrame, camping, and anything that gets me outdoors! I am also a registered yoga teacher and have been practicing for over six years.\r\n\r\n\r\n\r\n",
    "preview": {},
    "last_modified": "2022-04-20T14:39:36-07:00",
    "input_file": {}
  }
]
